practice-circuits/counter.v
`default_nettype none

module counter (
    clk_in,
    n_rst,
    start,
    inc_step,
    inc,
    dec,
    val_out
);
    input wire clk_in;
    input wire n_rst;
    input wire[3:0] start;
    input wire[2:0] inc_step;
    input wire inc;
    input wire dec;
    output reg[3:0] val_out;

    always @ (posedge clk_in, negedge n_rst) begin
        if (~n_rst)  begin
            val_out <= start;
        end else if (inc) begin
            val_out <= val_out + inc_step;
        end else if (dec) begin
            val_out <= val_out - inc_step;
        end
    end
endmodule

practice-circuits/counter-trace.vcd
$version Generated by VerilatedVcd $end
$timescale 1ps $end
 $scope module TOP $end
  $var wire 1 # clk_in $end
  $var wire 1 $ n_rst $end
  $var wire 4 % start [3:0] $end
  $var wire 3 & inc_step [2:0] $end
  $var wire 1 ' inc $end
  $var wire 1 ( dec $end
  $var wire 4 ) val_out [3:0] $end
  $scope module counter $end
   $var wire 1 # clk_in $end
   $var wire 1 $ n_rst $end
   $var wire 4 % start [3:0] $end
   $var wire 3 & inc_step [2:0] $end
   $var wire 1 ' inc $end
   $var wire 1 ( dec $end
   $var wire 4 ) val_out [3:0] $end
  $upscope $end
 $upscope $end
$enddefinitions $end


#0
1#
0$
b0011 %
b010 &
1'
0(
b0000 )
#1
0#
1$
#2
1#
0'
1(
b1110 )
#3
0#
#4
1#
1'
0(
b0000 )
#5
0#
#6
1#
b0010 )
#7
0#
0'
1(
#8
1#
1'
0(
b0100 )
#9
0#
0'
1(
#10
1#
b0010 )
#11
0#
#12
1#
b0000 )
#13
0#
#14
1#
b1110 )
#15
0#
1'
0(
#16
1#
b0000 )
#17
0#
#18
1#
0'
1(
b1110 )
#19
0#
#20
1#
b1100 )
#21
0#
#22
1#
b1010 )
#23
0#
1'
0(
#24
1#
b1100 )
#25
0#
#26
1#
0'
1(
b1010 )
#27
0#
#28
1#
b1000 )
#29
0#
1'
0(
#30
1#
0'
1(
b0110 )
#31
0#
1'
0(
#32
1#
b1000 )
#33
0#
#34
1#
0'
1(
b0110 )
#35
0#
1'
0(
#36
1#
0'
1(
b0100 )
#37
0#
#38
1#
1'
0(
b0110 )
#39
0#
0'
1(
#40
1#
b0100 )
#41
0#
#42
1#
b0010 )
#43
0#
#44
1#
b0000 )
#45
0#
1'
0(
#46
1#
b0010 )
#47
0#
0'
1(
#48
1#
1'
0(
b0100 )
#49
0#
0'
1(
#50
1#
b0010 )
#51
0#
#52
1#
1'
0(
b0100 )
#53
0#
0'
1(
#54
1#
b0010 )
#55
0#
1'
0(
#56
1#
0'
1(
b0000 )
#57
0#
1'
0(
#58
1#
b0010 )
#59
0#
0'
1(
#60
1#
b0000 )
#61
0#
#62
1#
b1110 )
#63
0#
#64
1#
1'
0(
b0000 )
#65
0#
0'
1(
#66
1#
b1110 )
#67
0#
1'
0(
#68
1#
b0000 )
#69
0#
#70
1#
0'
1(
b1110 )
#71
0#
#72
1#
b1100 )
#73
0#
1'
0(
#74
1#
b1110 )
#75
0#
#76
1#
b0000 )
#77
0#
#78
1#
b0010 )
#79
0#
0'
1(
#80
1#
1'
0(
b0100 )
#81
0#
0'
1(
#82
1#
1'
0(
b0110 )
#83
0#
0'
1(
#84
1#
1'
0(
b1000 )
#85
0#
#86
1#
b1010 )
#87
0#
0'
1(
#88
1#
b1000 )
#89
0#
1'
0(
#90
1#
0'
1(
b0110 )
#91
0#
#92
1#
b0100 )
#93
0#
#94
1#
b0010 )
#95
0#
#96
1#
b0000 )
#97
0#
1'
0(
#98
1#
b0010 )
#99
0#
#100
1#
0$
b0011 )
#101
0#
1$
#102
1#
b0101 )
#103
0#
0'
1(
#104
1#
b0011 )
#105
0#
1'
0(
#106
1#
0'
1(
b0001 )
#107
0#
#108
1#
1'
0(
b0011 )
#109
0#
#110
1#
b0101 )
#111
0#
0'
1(
#112
1#
b0011 )
#113
0#
#114
1#
b0001 )
#115
0#
#116
1#
1'
0(
b0011 )
#117
0#
0'
1(
#118
1#
b0001 )
#119
0#
1'
0(
#120
1#
0'
1(
b1111 )
#121
0#
#122
1#
b1101 )
#123
0#
#124
1#
b1011 )
#125
0#
#126
1#
b1001 )
#127
0#
#128
1#
1'
0(
b1011 )
#129
0#
#130
1#
b1101 )
#131
0#
0'
1(
#132
1#
1'
0(
b1111 )
#133
0#
0'
1(
#134
1#
b1101 )
#135
0#
#136
1#
1'
0(
b1111 )
#137
0#
0'
1(
#138
1#
b1101 )
#139
0#
#140
1#
1'
0(
b1111 )
#141
0#
#142
1#
0'
1(
b1101 )
#143
0#
#144
1#
b1011 )
#145
0#
#146
1#
b1001 )
#147
0#
#148
1#
1'
0(
b1011 )
#149
0#
#150
1#
0'
1(
b1001 )
#151
0#
#152
1#
1'
0(
b1011 )
#153
0#
#154
1#
0'
1(
b1001 )
#155
0#
1'
0(
#156
1#
0'
1(
b0111 )
#157
0#
#158
1#
1'
0(
b1001 )
#159
0#
#160
1#
0'
1(
b0111 )
#161
0#
#162
1#
1'
0(
b1001 )
#163
0#
0'
1(
#164
1#
1'
0(
b1011 )
#165
0#
0'
1(
#166
1#
b1001 )
#167
0#
1'
0(
#168
1#
b1011 )
#169
0#
#170
1#
b1101 )
#171
0#
#172
1#
b1111 )
#173
0#
#174
1#
b0001 )
#175
0#
0'
1(
#176
1#
b1111 )
#177
0#
#178
1#
1'
0(
b0001 )
#179
0#
#180
1#
b0011 )
#181
0#
0'
1(
#182
1#
b0001 )
#183
0#
1'
0(
#184
1#
0'
1(
b1111 )
#185
0#
1'
0(
#186
1#
b0001 )
#187
0#
0'
1(
#188
1#
1'
0(
b0011 )
#189
0#
#190
1#
b0101 )
#191
0#
#192
1#
0'
1(
b0011 )
#193
0#
1'
0(
#194
1#
0'
1(
b0001 )
#195
0#
#196
1#
1'
0(
b0011 )
#197
0#
0'
1(
#198
1#
b0001 )
#199
0#
#200
1#
0$
b0011 )
#201
0#
1$
#202
1#
1'
0(
b0101 )
#203
0#
#204
1#
0'
1(
b0011 )
#205
0#
1'
0(
#206
1#
0'
1(
b0001 )
#207
0#
1'
0(
#208
1#
b0011 )
#209
0#
#210
1#
0'
1(
b0001 )
#211
0#
1'
0(
#212
1#
0'
1(
b1111 )
#213
0#
1'
0(
#214
1#
0'
1(
b1101 )
#215
0#
#216
1#
1'
0(
b1111 )
#217
0#
0'
1(
#218
1#
1'
0(
b0001 )
#219
0#
#220
1#
0'
1(
b1111 )
#221
0#
#222
1#
1'
0(
b0001 )
#223
0#
#224
1#
b0011 )
#225
0#
0'
1(
#226
1#
b0001 )
#227
0#
1'
0(
#228
1#
0'
1(
b1111 )
#229
0#
#230
1#
b1101 )
#231
0#
1'
0(
#232
1#
b1111 )
#233
0#
0'
1(
#234
1#
1'
0(
b0001 )
#235
0#
0'
1(
#236
1#
1'
0(
b0011 )
#237
0#
0'
1(
#238
1#
1'
0(
b0101 )
#239
0#
#240
1#
b0111 )
#241
0#
#242
1#
b1001 )
#243
0#
#244
1#
0'
1(
b0111 )
#245
0#
1'
0(
#246
1#
b1001 )
#247
0#
#248
1#
b1011 )
#249
0#
#250
1#
b1101 )
#251
0#
#252
1#
0'
1(
b1011 )
#253
0#
1'
0(
#254
1#
b1101 )
#255
0#
0'
1(
#256
1#
1'
0(
b1111 )
#257
0#
0'
1(
#258
1#
b1101 )
#259
0#
1'
0(
#260
1#
b1111 )
#261
0#
#262
1#
0'
1(
b1101 )
#263
0#
#264
1#
b1011 )
#265
0#
#266
1#
1'
0(
b1101 )
#267
0#
0'
1(
#268
1#
1'
0(
b1111 )
#269
0#
0'
1(
#270
1#
b1101 )
#271
0#
1'
0(
#272
1#
b1111 )
#273
0#
#274
1#
0'
1(
b1101 )
#275
0#
#276
1#
b1011 )
#277
0#
1'
0(
#278
1#
0'
1(
b1001 )
#279
0#
1'
0(
#280
1#
0'
1(
b0111 )
#281
0#
1'
0(
#282
1#
b1001 )
#283
0#
#284
1#
0'
1(
b0111 )
#285
0#
1'
0(
#286
1#
0'
1(
b0101 )
#287
0#
1'
0(
#288
1#
b0111 )
#289
0#
0'
1(
#290
1#
1'
0(
b1001 )
#291
0#
0'
1(
#292
1#
b0111 )
#293
0#
#294
1#
1'
0(
b1001 )
#295
0#
#296
1#
0'
1(
b0111 )
#297
0#
1'
0(
#298
1#
b1001 )
