practice-circuits/tff.v
`default_nettype none

// DFF with async reset
module tff (
    clk,
    t_in,
    n_reset,
    data_out
);

    input wire clk;
    input wire t_in;
    input wire n_reset;
    output reg data_out;

    always @ (posedge clk or negedge n_reset) begin
        if (~n_reset) begin
            data_out <= 0;
        end else begin
            if (t_in) begin
                data_out <= ~data_out;
            end
        end
    end
endmodule

practice-circuits/dff-trace.vcd
$version Generated by VerilatedVcd $end
$timescale 1ps $end
 $scope module TOP $end
  $var wire 1 # clk $end
  $var wire 1 $ t_in $end
  $var wire 1 % n_reset $end
  $var wire 1 & data_out $end
  $scope module tff $end
   $var wire 1 # clk $end
   $var wire 1 $ t_in $end
   $var wire 1 % n_reset $end
   $var wire 1 & data_out $end
  $upscope $end
 $upscope $end
$enddefinitions $end


#0
1#
1$
1%
0&
#1
0#
0%
#2
1#
1%
1&
#3
0#
0$
0%
0&
#4
1#
1%
#5
0#
1$
0%
#6
1#
0$
1%
#7
0#
1$
#8
1#
0%
#9
0#
0$
#10
1#
1$
#11
0#
1%
#12
1#
0%
#13
0#
0$
1%
#14
1#
1$
0%
#15
0#
0$
#16
1#
1$
1%
1&
#17
0#
#18
1#
0$
#19
0#
1$
#20
1#
0%
0&
#21
0#
#22
1#
0$
1%
#23
0#
1$
0%
#24
1#
0$
#25
0#
#26
1#
1$
1%
1&
#27
0#
#28
1#
0$
#29
0#
0%
0&
#30
1#
1$
1%
1&
#31
0#
#32
1#
0$
#33
0#
1$
0%
0&
#34
1#
1%
1&
#35
0#
0%
0&
#36
1#
0$
#37
0#
1$
#38
1#
1%
1&
#39
0#
#40
1#
0%
0&
#41
0#
0$
1%
#42
1#
1$
1&
#43
0#
0%
0&
#44
1#
0$
#45
0#
1$
#46
1#
#47
0#
#48
1#
#49
0#
0$
1%
#50
1#
1$
1&
#51
0#
0%
0&
#52
1#
0$
1%
#53
0#
1$
0%
#54
1#
0$
1%
#55
0#
1$
#56
1#
1&
#57
0#
#58
1#
0$
0%
0&
#59
0#
1%
#60
1#
1$
0%
#61
0#
#62
1#
0$
#63
0#
1$
1%
#64
1#
0$
#65
0#
1$
0%
#66
1#
0$
1%
#67
0#
#68
1#
1$
1&
#69
0#
0$
#70
1#
#71
0#
1$
0%
0&
#72
1#
1%
1&
#73
0#
0$
0%
0&
#74
1#
1$
#75
0#
1%
#76
1#
0%
#77
0#
0$
1%
#78
1#
1$
0%
#79
0#
#80
1#
0$
1%
#81
0#
1$
0%
#82
1#
0$
#83
0#
1$
1%
#84
1#
0$
#85
0#
1$
#86
1#
0$
0%
#87
0#
1$
#88
1#
0$
1%
#89
0#
0%
#90
1#
1$
1%
1&
#91
0#
#92
1#
0$
0%
0&
#93
0#
1%
#94
1#
0%
#95
0#
1$
#96
1#
1%
1&
#97
0#
#98
1#
0&
#99
0#
0%
#100
1#
1%
1&
#101
0#
0$
#102
1#
1$
0&
#103
0#
0$
#104
1#
1$
0%
#105
0#
1%
#106
1#
0$
0%
#107
0#
1%
#108
1#
1$
1&
#109
0#
0%
0&
#110
1#
0$
#111
0#
1$
#112
1#
0$
1%
#113
0#
#114
1#
1$
1&
#115
0#
#116
1#
0$
#117
0#
1$
0%
0&
#118
1#
0$
#119
0#
1%
#120
1#
1$
1&
#121
0#
0%
0&
#122
1#
0$
#123
0#
#124
1#
#125
0#
1$
#126
1#
0$
#127
0#
1%
#128
1#
0%
#129
0#
1$
1%
#130
1#
0$
0%
#131
0#
1$
1%
#132
1#
0%
#133
0#
0$
1%
#134
1#
0%
#135
0#
1$
1%
#136
1#
0$
0%
#137
0#
1%
#138
1#
1$
1&
#139
0#
0%
0&
#140
1#
0$
1%
#141
0#
0%
#142
1#
#143
0#
1$
1%
#144
1#
1&
#145
0#
0$
0%
0&
#146
1#
1$
1%
1&
#147
0#
0%
0&
#148
1#
#149
0#
1%
#150
1#
1&
#151
0#
0%
0&
#152
1#
1%
1&
#153
0#
0$
#154
1#
#155
0#
#156
1#
0%
0&
#157
0#
#158
1#
1$
1%
1&
#159
0#
#160
1#
0&
#161
0#
0%
#162
1#
1%
1&
#163
0#
#164
1#
0&
#165
0#
0%
#166
1#
#167
0#
#168
1#
#169
0#
#170
1#
0$
1%
#171
0#
#172
1#
1$
1&
#173
0#
#174
1#
0%
0&
#175
0#
#176
1#
0$
1%
#177
0#
0%
#178
1#
#179
0#
#180
1#
#181
0#
1$
#182
1#
#183
0#
#184
1#
1%
1&
#185
0#
0$
0%
0&
#186
1#
1$
1%
1&
#187
0#
#188
1#
0$
#189
0#
#190
1#
1$
0&
#191
0#
#192
1#
0$
#193
0#
#194
1#
1$
1&
#195
0#
0$
#196
1#
1$
0%
0&
#197
0#
0$
1%
#198
1#
#199
0#
1$
0%
#200
1#
#201
0#
#202
1#
0$
#203
0#
1%
#204
1#
#205
0#
0%
#206
1#
1%
#207
0#
0%
#208
1#
1$
1%
1&
#209
0#
0$
#210
1#
#211
0#
#212
1#
1$
0&
#213
0#
0$
#214
1#
0%
#215
0#
1$
#216
1#
0$
1%
#217
0#
0%
#218
1#
1$
1%
1&
#219
0#
0%
0&
#220
1#
0$
#221
0#
#222
1#
1$
#223
0#
0$
1%
#224
1#
#225
0#
1$
#226
1#
0$
#227
0#
1$
0%
#228
1#
1%
1&
#229
0#
0$
#230
1#
#231
0#
0%
0&
#232
1#
1$
1%
1&
#233
0#
0$
#234
1#
0%
0&
#235
0#
1$
#236
1#
0$
#237
0#
1%
#238
1#
#239
0#
0%
#240
1#
1$
#241
0#
0$
1%
#242
1#
1$
1&
#243
0#
#244
1#
0%
0&
#245
0#
#246
1#
0$
#247
0#
1$
1%
#248
1#
0$
0%
#249
0#
1$
1%
#250
1#
0$
#251
0#
1$
0%
#252
1#
0$
1%
#253
0#
1$
#254
1#
0$
#255
0#
1$
0%
#256
1#
0$
#257
0#
1$
1%
#258
1#
0$
0%
#259
0#
1%
#260
1#
0%
#261
0#
1$
1%
#262
1#
0%
#263
0#
0$
1%
#264
1#
1$
0%
#265
0#
1%
#266
1#
0$
0%
#267
0#
1$
#268
1#
0$
1%
#269
0#
#270
1#
#271
0#
1$
0%
#272
1#
#273
0#
0$
#274
1#
#275
0#
1$
#276
1#
#277
0#
#278
1#
0$
#279
0#
1$
#280
1#
1%
1&
#281
0#
0%
0&
#282
1#
1%
1&
#283
0#
0%
0&
#284
1#
0$
#285
0#
1$
1%
#286
1#
0$
#287
0#
1$
#288
1#
1&
#289
0#
#290
1#
0&
#291
0#
0$
0%
#292
1#
1%
#293
0#
1$
0%
#294
1#
#295
0#
#296
1#
1%
1&
#297
0#
0$
#298
1#
1$
0%
0&
#299
0#
1%
