practice-circuits/encoder.v
`default_nettype none

// 16-to-4 Encoder
module encoder(
    raw_in,
    bcd_out,
    enable
);

    input wire[15:0] raw_in;
    input wire enable;

    output reg[3:0] bcd_out;

    always @ (enable) begin
        bcd_out = 0;
        if (enable) begin
            casex (raw_in)
                default: bcd_out = 4'd0;
                16'b1???????????????: bcd_out = 4'd15;
                16'b01??????????????: bcd_out = 4'd14;
                16'b001?????????????: bcd_out = 4'd13;
                16'b0001????????????: bcd_out = 4'd12;
                16'b00001???????????: bcd_out = 4'd11;
                16'b000001??????????: bcd_out = 4'd10;
                16'b0000001?????????: bcd_out = 4'd9;
                16'b00000001????????: bcd_out = 4'd8;
                16'b000000001???????: bcd_out = 4'd7;
                16'b0000000001??????: bcd_out = 4'd6;
                16'b00000000001?????: bcd_out = 4'd5;
                16'b000000000001????: bcd_out = 4'd4;
                16'b0000000000001???: bcd_out = 4'd3;
                16'b00000000000001??: bcd_out = 4'd2;
                16'b000000000000001?: bcd_out = 4'd1;
            endcase
        end
    end
endmodule

practice-circuits/encoder-trace.vcd
$version Generated by VerilatedVcd $end
$timescale 1ps $end
 $scope module TOP $end
  $var wire 16 # raw_in [15:0] $end
  $var wire 1 $ enable $end
  $var wire 4 % bcd_out [3:0] $end
  $scope module encoder $end
   $var wire 16 # raw_in [15:0] $end
   $var wire 1 $ enable $end
   $var wire 4 % bcd_out [3:0] $end
  $upscope $end
 $upscope $end
$enddefinitions $end


#0
b0000000000000000 #
1$
b0000 %
#10
b0000000000000001 #
#20
b0000000000000010 #
b0001 %
#30
b0000000000000011 #
#40
b0000000000000100 #
b0010 %
#50
b0000000000000101 #
#60
b0000000000000110 #
#70
b0000000000000111 #
#80
b0000000000001000 #
b0011 %
#90
b0000000000001001 #
#100
b0000000000001010 #
#110
b0000000000001011 #
#120
b0000000000001100 #
#130
b0000000000001101 #
#140
b0000000000001110 #
#150
b0000000000001111 #
#160
b0000000000010000 #
b0100 %
#170
b0000000000010001 #
#180
b0000000000010010 #
#190
b0000000000010011 #
