practice-circuits/encoder.v
`default_nettype none

// 16-to-4 Encoder
module encoder(
    encoded_in,
    bcd_out,
    enable
);

    input wire[16:0] encoded_in;
    input wire enable;

    output reg[4:0] bcd_out;

    always @ (enable) begin
        bcd_out = 0;
        if (enable) begin

            if (encoded_in == 16'd2) begin
                bcd_out = 4'd1;
            end if (encoded_in == 16'd4) begin
                bcd_out = 4'd2;
            end if (encoded_in == 16'd8) begin
                bcd_out = 4'd3;
            end if (encoded_in == 16'd16) begin
                bcd_out = 4'd4;
            end if (encoded_in == 16'd32) begin
                bcd_out = 4'd5;
            end if (encoded_in == 16'd64) begin
                bcd_out = 4'd6;
            end if (encoded_in == 16'd128) begin
                bcd_out = 4'd7;
            end if (encoded_in == 16'd256) begin
                bcd_out = 4'd8;
            end if (encoded_in == 16'd512) begin
                bcd_out = 4'd9;
            end if (encoded_in == 16'd1024) begin
                bcd_out = 4'd10;
            end if (encoded_in == 16'd2048) begin
                bcd_out = 4'd11;
            end if (encoded_in == 16'd4096) begin
                bcd_out = 4'd12;
            end if (encoded_in == 16'd8192) begin
                bcd_out = 4'd13;
            end if (encoded_in == 16'd16384) begin
                bcd_out = 4'd14;
            end if (encoded_in == 16'd32768) begin
                bcd_out = 4'd15;
            end

        end
    end
endmodule

practice-circuits/encoder-trace.vcd
$version Generated by VerilatedVcd $end
$timescale 1ps $end
 $scope module TOP $end
  $var wire 17 # encoded_in [16:0] $end
  $var wire 1 $ enable $end
  $var wire 5 % bcd_out [4:0] $end
  $scope module encoder $end
   $var wire 17 # encoded_in [16:0] $end
   $var wire 1 $ enable $end
   $var wire 5 % bcd_out [4:0] $end
  $upscope $end
 $upscope $end
$enddefinitions $end


#0
b00000000000000001 #
1$
b00000 %
#10
b00000000000000010 #
0$
#20
b00000000000000100 #
1$
b00010 %
#30
b00000000000001000 #
0$
b00000 %
#40
b00000000000010000 #
1$
b00100 %
#50
b00000000000100000 #
0$
b00000 %
#60
b00000000001000000 #
1$
b00110 %
#70
b00000000010000000 #
0$
b00000 %
#80
b00000000100000000 #
1$
b01000 %
#90
b00000001000000000 #
0$
b00000 %
#100
b00000010000000000 #
1$
b01010 %
#110
b00000100000000000 #
0$
b00000 %
#120
b00001000000000000 #
1$
b01100 %
#130
b00010000000000000 #
0$
b00000 %
#140
b00100000000000000 #
1$
b01110 %
#150
b01000000000000000 #
0$
b00000 %
#160
b10000000000000000 #
1$
#170
b00000000000000000 #
0$
#180
b00000000000000000 #
1$
#190
b00000000000000000 #
0$
