practice-circuits/latch.v
`default_nettype none

// DFF with async reset
module latch (
    en_in,
    d_in,
    n_rst_in,
    q_out
);

    input wire en_in;
    input wire d_in;
    input wire n_rst_in;
    output reg q_out;

    always @ (
        en_in,
        d_in,
        n_rst_in,
        q_out
    ) begin
        if (~n_rst_in) begin
            q_out <= 0;
        end else if (en_in) begin
            q_out <= d_in;
        end
    end
endmodule

practice-circuits/ff.v
`default_nettype none
`include "latch.v"

// DFF built using d-latch
module ff (
    clk_in,
    d_in,
    n_rst_in,
    q_out
);

    input wire clk_in;
    input wire d_in;
    input wire n_rst_in;

    output reg q_out;

    // Internal signals
    wire mosi;

    latch master_latch(
        .en_in      (~clk_in),
        .d_in       (d_in),
        .n_rst_in   (n_rst_in),
        .q_out      (mosi)
    );

    latch slave_latch(
        .en_in      (clk_in),
        .d_in       (mosi),
        .n_rst_in   (n_rst_in),
        .q_out      (q_out)
    );

endmodule

practice-circuits/ff-trace.vcd
$version Generated by VerilatedVcd $end
$timescale 1ps $end
 $scope module TOP $end
  $var wire 1 # clk_in $end
  $var wire 1 $ d_in $end
  $var wire 1 % n_rst_in $end
  $var wire 1 & q_out $end
  $scope module ff $end
   $var wire 1 # clk_in $end
   $var wire 1 $ d_in $end
   $var wire 1 % n_rst_in $end
   $var wire 1 & q_out $end
   $var wire 1 ' mosi $end
   $scope module master_latch $end
    $var wire 1 ( en_in $end
    $var wire 1 $ d_in $end
    $var wire 1 % n_rst_in $end
    $var wire 1 ' q_out $end
   $upscope $end
   $scope module slave_latch $end
    $var wire 1 # en_in $end
    $var wire 1 ' d_in $end
    $var wire 1 % n_rst_in $end
    $var wire 1 & q_out $end
   $upscope $end
  $upscope $end
 $upscope $end
$enddefinitions $end


#0
1#
0$
0%
0&
0'
0(
#1
0#
1$
1%
1'
1(
#2
1#
1&
0(
#3
0#
1(
#4
1#
0$
0(
#5
0#
1$
1(
#6
1#
0(
#7
0#
1(
#8
1#
0$
0(
#9
0#
1$
1(
#10
1#
0(
#11
0#
1(
#12
1#
0(
#13
0#
0$
0'
1(
#14
1#
0&
0(
#15
0#
1$
1'
1(
#16
1#
1&
0(
#17
0#
0$
0'
1(
#18
1#
0&
0(
#19
0#
1(
#20
1#
0(
#21
0#
1$
1'
1(
#22
1#
1&
0(
#23
0#
1(
#24
1#
0$
0(
#25
0#
0'
1(
#26
1#
0&
0(
#27
0#
1(
#28
1#
1$
0(
#29
0#
0$
1(
#30
1#
1$
0(
#31
0#
0$
1(
#32
1#
0(
#33
0#
1(
#34
1#
0(
#35
0#
1$
1'
1(
#36
1#
1&
0(
#37
0#
1(
#38
1#
0$
0(
#39
0#
1$
1(
#40
1#
0$
0(
#41
0#
0'
1(
#42
1#
1$
0&
0(
#43
0#
1'
1(
#44
1#
0$
1&
0(
#45
0#
1$
1(
#46
1#
0$
0(
#47
0#
0'
1(
#48
1#
0&
0(
#49
0#
1$
1'
1(
#50
1#
0$
1&
0(
#51
0#
1$
1(
#52
1#
0$
0(
#53
0#
1$
1(
#54
1#
0$
0(
#55
0#
0'
1(
#56
1#
0&
0(
#57
0#
1(
#58
1#
1$
0(
#59
0#
0$
1(
#60
1#
0(
#61
0#
1(
#62
1#
0(
#63
0#
1$
1'
1(
#64
1#
0$
1&
0(
#65
0#
0'
1(
#66
1#
1$
0&
0(
#67
0#
1'
1(
#68
1#
0$
1&
0(
#69
0#
0'
1(
#70
1#
1$
0&
0(
#71
0#
0$
1(
#72
1#
1$
0(
#73
0#
1'
1(
#74
1#
0$
1&
0(
#75
0#
1$
1(
#76
1#
0$
0(
#77
0#
1$
1(
#78
1#
0(
#79
0#
1(
#80
1#
0(
#81
0#
1(
#82
1#
0$
0(
#83
0#
1$
1(
#84
1#
0$
0(
#85
0#
1$
1(
#86
1#
0$
0(
#87
0#
1$
1(
#88
1#
0(
#89
0#
0$
0'
1(
#90
1#
0&
0(
#91
0#
1(
#92
1#
0(
#93
0#
1(
#94
1#
0(
#95
0#
1$
1'
1(
#96
1#
1&
0(
#97
0#
1(
#98
1#
0(
#99
0#
0$
0'
1(
#100
1#
0%
0&
0(
#101
0#
1%
1(
#102
1#
1$
0(
#103
0#
0$
1(
#104
1#
0(
#105
0#
1(
#106
1#
1$
0(
#107
0#
1'
1(
#108
1#
1&
0(
#109
0#
1(
#110
1#
0$
0(
#111
0#
0'
1(
#112
1#
0&
0(
#113
0#
1$
1'
1(
#114
1#
1&
0(
#115
0#
0$
0'
1(
#116
1#
0&
0(
#117
0#
1(
#118
1#
1$
0(
#119
0#
0$
1(
#120
1#
1$
0(
#121
0#
0$
1(
#122
1#
1$
0(
#123
0#
0$
1(
#124
1#
0(
#125
0#
1$
1'
1(
#126
1#
1&
0(
#127
0#
0$
0'
1(
#128
1#
0&
0(
#129
0#
1$
1'
1(
#130
1#
0$
1&
0(
#131
0#
1$
1(
#132
1#
0(
#133
0#
1(
#134
1#
0(
#135
0#
0$
0'
1(
#136
1#
0&
0(
#137
0#
1(
#138
1#
1$
0(
#139
0#
0$
1(
#140
1#
0(
#141
0#
1(
#142
1#
1$
0(
#143
0#
0$
1(
#144
1#
1$
0(
#145
0#
1'
1(
#146
1#
0$
1&
0(
#147
0#
0'
1(
#148
1#
1$
0&
0(
#149
0#
1'
1(
#150
1#
1&
0(
#151
0#
0$
0'
1(
#152
1#
1$
0&
0(
#153
0#
1'
1(
#154
1#
1&
0(
#155
0#
1(
#156
1#
0$
0(
#157
0#
0'
1(
#158
1#
0&
0(
#159
0#
1(
#160
1#
1$
0(
#161
0#
1'
1(
#162
1#
0$
1&
0(
#163
0#
0'
1(
#164
1#
1$
0&
0(
#165
0#
1'
1(
#166
1#
1&
0(
#167
0#
1(
#168
1#
0$
0(
#169
0#
0'
1(
#170
1#
0&
0(
#171
0#
1$
1'
1(
#172
1#
0$
1&
0(
#173
0#
0'
1(
#174
1#
1$
0&
0(
#175
0#
0$
1(
#176
1#
1$
0(
#177
0#
1'
1(
#178
1#
1&
0(
#179
0#
1(
#180
1#
0(
#181
0#
1(
#182
1#
0$
0(
#183
0#
1$
1(
#184
1#
0$
0(
#185
0#
1$
1(
#186
1#
0(
#187
0#
1(
#188
1#
0$
0(
#189
0#
1$
1(
#190
1#
0(
#191
0#
0$
0'
1(
#192
1#
1$
0&
0(
#193
0#
1'
1(
#194
1#
0$
1&
0(
#195
0#
1$
1(
#196
1#
0$
0(
#197
0#
1$
1(
#198
1#
0$
0(
#199
0#
0'
1(
#200
1#
0%
0&
0(
#201
0#
1$
1%
1'
1(
#202
1#
1&
0(
#203
0#
1(
#204
1#
0$
0(
#205
0#
1$
1(
#206
1#
0(
#207
0#
1(
#208
1#
0(
#209
0#
1(
#210
1#
0(
#211
0#
0$
0'
1(
#212
1#
1$
0&
0(
#213
0#
1'
1(
#214
1#
1&
0(
#215
0#
1(
#216
1#
0$
0(
#217
0#
0'
1(
#218
1#
0&
0(
#219
0#
1$
1'
1(
#220
1#
0$
1&
0(
#221
0#
0'
1(
#222
1#
1$
0&
0(
#223
0#
1'
1(
#224
1#
1&
0(
#225
0#
0$
0'
1(
#226
1#
0&
0(
#227
0#
1$
1'
1(
#228
1#
1&
0(
#229
0#
0$
0'
1(
#230
1#
1$
0&
0(
#231
0#
1'
1(
#232
1#
0$
1&
0(
#233
0#
0'
1(
#234
1#
0&
0(
#235
0#
1(
#236
1#
0(
#237
0#
1(
#238
1#
0(
#239
0#
1(
#240
1#
1$
0(
#241
0#
1'
1(
#242
1#
0$
1&
0(
#243
0#
1$
1(
#244
1#
0(
#245
0#
1(
#246
1#
0(
#247
0#
1(
#248
1#
0$
0(
#249
0#
1$
1(
#250
1#
0(
#251
0#
0$
0'
1(
#252
1#
1$
0&
0(
#253
0#
1'
1(
#254
1#
0$
1&
0(
#255
0#
1$
1(
#256
1#
0(
#257
0#
1(
#258
1#
0$
0(
#259
0#
0'
1(
#260
1#
0&
0(
#261
0#
1$
1'
1(
#262
1#
0$
1&
0(
#263
0#
0'
1(
#264
1#
0&
0(
#265
0#
1(
#266
1#
1$
0(
#267
0#
0$
1(
#268
1#
0(
#269
0#
1$
1'
1(
#270
1#
0$
1&
0(
#271
0#
1$
1(
#272
1#
0$
0(
#273
0#
0'
1(
#274
1#
0&
0(
#275
0#
1(
#276
1#
0(
#277
0#
1(
#278
1#
1$
0(
#279
0#
1'
1(
#280
1#
1&
0(
#281
0#
1(
#282
1#
0$
0(
#283
0#
0'
1(
#284
1#
1$
0&
0(
#285
0#
0$
1(
#286
1#
0(
#287
0#
1$
1'
1(
#288
1#
0$
1&
0(
#289
0#
0'
1(
#290
1#
1$
0&
0(
#291
0#
0$
1(
#292
1#
1$
0(
#293
0#
0$
1(
#294
1#
1$
0(
#295
0#
1'
1(
#296
1#
0$
1&
0(
#297
0#
1$
1(
#298
1#
0(
#299
0#
1(
