practice-circuits/latch.v
`default_nettype none

// DFF with async reset
module latch (
    en_in,
    d_in,
    n_rst_in,
    q_out
);

    input wire en_in;
    input wire d_in;
    input wire n_rst_in;
    output reg q_out;

    always @ (
        en_in,
        d_in,
        n_rst_in,
        q_out
    ) begin
        if (~n_rst_in) begin
            q_out <= 0;
        end else if (en_in) begin
            q_out <= d_in;
        end
    end
endmodule

practice-circuits/latch-trace.vcd
$version Generated by VerilatedVcd $end
$timescale 1ps $end
 $scope module TOP $end
  $var wire 1 # en_in $end
  $var wire 1 $ d_in $end
  $var wire 1 % n_rst_in $end
  $var wire 1 & q_out $end
  $scope module latch $end
   $var wire 1 # en_in $end
   $var wire 1 $ d_in $end
   $var wire 1 % n_rst_in $end
   $var wire 1 & q_out $end
  $upscope $end
 $upscope $end
$enddefinitions $end


#0
1#
0$
0%
0&
#1
0#
1$
1%
#2
1#
1&
#3
0$
0&
#4
0#
1$
#5
1#
0$
#6
0#
1$
#7
1#
1&
#8
0$
0&
#9
0#
1$
#10
0$
#11
#12
#13
1#
#14
0#
#15
#16
1$
#17
1#
1&
#18
0#
#19
#20
#21
#22
0$
#23
1#
1$
#24
#25
0#
#26
1#
#27
#28
0#
#29
1#
#30
0#
#31
0$
#32
#33
1#
1$
#34
#35
0#
#36
#37
0$
#38
1#
1$
#39
0#
0$
#40
1$
#41
0$
#42
1#
0&
#43
0#
1$
#44
1#
0$
#45
0#
1$
#46
1#
1&
#47
#48
0#
#49
0$
#50
#51
1#
1$
#52
0$
0&
#53
0#
#54
1#
#55
1$
1&
#56
0#
#57
1#
0$
0&
#58
1$
1&
#59
0#
#60
1#
0$
0&
#61
#62
1$
1&
#63
#64
0#
0$
#65
1$
#66
#67
1#
0$
0&
#68
#69
#70
0#
1$
#71
1#
1&
#72
0$
0&
#73
#74
#75
#76
#77
0#
1$
#78
0$
#79
1$
#80
#81
0$
#82
#83
1#
#84
0#
1$
#85
1#
1&
#86
0#
0$
#87
1#
0&
#88
1$
1&
#89
0#
#90
0$
#91
1#
0&
#92
#93
#94
0#
1$
#95
0$
#96
1#
#97
0#
#98
1#
1$
1&
#99
0$
0&
#100
0%
#101
0#
1%
#102
#103
1#
#104
#105
1$
1&
#106
0$
0&
#107
0#
#108
1#
1$
1&
#109
0#
0$
#110
1$
#111
1#
#112
0#
0$
#113
1#
0&
#114
0#
1$
#115
0$
#116
1#
1$
1&
#117
#118
0#
0$
#119
#120
1#
0&
#121
0#
1$
#122
0$
#123
1#
#124
0#
1$
#125
1#
1&
#126
0#
0$
#127
1#
1$
#128
0$
0&
#129
#130
#131
0#
1$
#132
1#
0$
#133
0#
1$
#134
#135
1#
0$
#136
#137
0#
#138
1#
1$
1&
#139
#140
0#
0$
#141
1#
0&
#142
#143
#144
1$
1&
#145
0#
0$
#146
1#
1$
#147
0#
0$
#148
1#
1$
#149
#150
0$
0&
#151
#152
0#
#153
1#
#154
#155
#156
1$
1&
#157
0$
0&
#158
1$
1&
#159
0#
#160
1#
#161
0$
0&
#162
0#
#163
1#
#164
1$
1&
#165
0$
0&
#166
1$
1&
#167
0$
0&
#168
0#
1$
#169
0$
#170
#171
1#
#172
1$
1&
#173
0$
0&
#174
0#
1$
#175
1#
1&
#176
0$
0&
#177
1$
1&
#178
0#
#179
0$
#180
1#
1$
#181
0#
0$
#182
1$
#183
1#
0$
0&
#184
0#
1$
#185
1#
0$
#186
0#
#187
1#
1$
1&
#188
0#
#189
#190
1#
#191
0#
0$
#192
1#
1$
#193
0$
0&
#194
0#
1$
#195
#196
1#
1&
#197
0$
0&
#198
#199
#200
0#
0%
#201
1#
1$
1%
1&
#202
0$
0&
#203
0#
1$
#204
1#
1&
#205
0$
0&
#206
0#
#207
1#
#208
1$
1&
#209
0#
#210
1#
0$
0&
#211
#212
1$
1&
#213
0$
0&
#214
1$
1&
#215
0$
0&
#216
0#
#217
#218
#219
1$
#220
0$
#221
1#
1$
1&
#222
0#
#223
1#
0$
0&
#224
0#
#225
1$
#226
#227
1#
0$
#228
0#
#229
1#
1$
1&
#230
0#
0$
#231
#232
1#
1$
#233
0$
0&
#234
1$
1&
#235
0#
#236
0$
#237
1#
0&
#238
0#
1$
#239
#240
0$
#241
1#
1$
1&
#242
0#
0$
#243
1#
0&
#244
1$
1&
#245
0#
#246
1#
#247
#248
0$
0&
#249
1$
1&
#250
0$
0&
#251
0#
1$
#252
#253
1#
1&
#254
0#
0$
#255
1#
1$
#256
#257
0$
0&
#258
1$
1&
#259
0#
0$
#260
1#
0&
#261
0#
1$
#262
1#
1&
#263
0#
0$
#264
1#
0&
#265
0#
#266
1#
1$
1&
#267
#268
0#
#269
#270
#271
1#
0$
0&
#272
0#
#273
1#
1$
1&
#274
0$
0&
#275
0#
#276
1#
#277
0#
#278
#279
1#
1$
1&
#280
0#
#281
0$
#282
1#
0&
#283
#284
0#
#285
1$
#286
0$
#287
#288
#289
#290
1#
#291
1$
1&
#292
0#
0$
#293
#294
1$
#295
#296
0$
#297
1#
0&
#298
#299
0#
