practice-circuits/mux.v
`default_nettype none

// 8-to-1 mux, 3 bit sel
module mux (
    data_0,
    data_1,
    data_2,
    data_3,
    data_4,
    data_5,
    data_6,
    data_7,
    sel,
    out
);
    input wire[2:0] data_0;
    input wire[2:0] data_1;
    input wire[2:0] data_2;
    input wire[2:0] data_3;
    input wire[2:0] data_4;
    input wire[2:0] data_5;
    input wire[2:0] data_6;
    input wire[2:0] data_7;
    input wire[2:0] sel;

    output reg[2:0] out;

    always @ (
        data_0,
        data_1,
        data_2,
        data_3,
        data_4,
        data_5,
        data_6,
        data_7,
        sel
    ) begin
        case (sel)
            default: out = 3'b111;
            3'b000: out = data_0;
            3'b001: out = data_1;
            3'b010: out = data_2;
            3'b011: out = data_3;
            3'b100: out = data_4;
            3'b101: out = data_5;
            3'b110: out = data_6;
            3'b111: out = data_7;
        endcase
    end

endmodule

practice-circuits/mux-trace.vcd
$version Generated by VerilatedVcd $end
$timescale 1ps $end
 $scope module TOP $end
  $var wire 3 # data_0 [2:0] $end
  $var wire 3 $ data_1 [2:0] $end
  $var wire 3 % data_2 [2:0] $end
  $var wire 3 & data_3 [2:0] $end
  $var wire 3 ' data_4 [2:0] $end
  $var wire 3 ( data_5 [2:0] $end
  $var wire 3 ) data_6 [2:0] $end
  $var wire 3 * data_7 [2:0] $end
  $var wire 3 + sel [2:0] $end
  $var wire 3 , out [2:0] $end
  $scope module mux $end
   $var wire 3 # data_0 [2:0] $end
   $var wire 3 $ data_1 [2:0] $end
   $var wire 3 % data_2 [2:0] $end
   $var wire 3 & data_3 [2:0] $end
   $var wire 3 ' data_4 [2:0] $end
   $var wire 3 ( data_5 [2:0] $end
   $var wire 3 ) data_6 [2:0] $end
   $var wire 3 * data_7 [2:0] $end
   $var wire 3 + sel [2:0] $end
   $var wire 3 , out [2:0] $end
  $upscope $end
 $upscope $end
$enddefinitions $end


#0
b000 #
b001 $
b010 %
b011 &
b100 '
b101 (
b110 )
b111 *
b000 +
b000 ,
#10
b001 +
b001 ,
#20
b010 +
b010 ,
#30
b011 +
b011 ,
#40
b100 +
b100 ,
#50
b101 +
b101 ,
#60
b110 +
b110 ,
#70
b111 +
b111 ,
#80
b000 +
b000 ,
#90
b001 +
b001 ,
#100
b010 +
b010 ,
#110
b011 +
b011 ,
#120
b100 +
b100 ,
#130
b101 +
b101 ,
#140
b110 +
b110 ,
#150
b111 +
b111 ,
#160
b000 +
b000 ,
#170
b001 +
b001 ,
#180
b010 +
b010 ,
#190
b011 +
b011 ,
