practice-circuits/shift_register.v
`default_nettype none

module shift_register(
    clk_in,
    n_rst_in,
    seq_in,
    seq_out,
    shift,
    parallel_in,
    parallel_out,
    parallel_load
);

    input wire clk_in;
    input wire n_rst_in;

    input wire seq_in;
    output reg seq_out;
    input wire shift;

    input wire[3:0] parallel_in;
    output reg[3:0] parallel_out;
    input wire parallel_load;

    reg[3:0] reg_val;

    assign seq_out = reg_val[0];
    assign parallel_out = reg_val;

    always @ (posedge clk_in, negedge n_rst_in) begin
        if (~n_rst_in) begin
            reg_val <= 0;
        end else if (parallel_load) begin
            reg_val <= parallel_in;
        end else if (shift) begin
            reg_val <= reg_val >> 1;
            reg_val[3] <= seq_in;
        end
    end

endmodule

practice-circuits/register-trace.vcd
$version Generated by VerilatedVcd $end
$timescale 1ps $end
 $scope module TOP $end
  $var wire 1 # clk_in $end
  $var wire 1 $ n_rst_in $end
  $var wire 1 % seq_in $end
  $var wire 1 & seq_out $end
  $var wire 1 ' shift $end
  $var wire 4 ( parallel_in [3:0] $end
  $var wire 4 ) parallel_out [3:0] $end
  $var wire 1 * parallel_load $end
  $scope module shift_register $end
   $var wire 1 # clk_in $end
   $var wire 1 $ n_rst_in $end
   $var wire 1 % seq_in $end
   $var wire 1 & seq_out $end
   $var wire 1 ' shift $end
   $var wire 4 ( parallel_in [3:0] $end
   $var wire 4 ) parallel_out [3:0] $end
   $var wire 1 * parallel_load $end
   $var wire 4 + reg_val [3:0] $end
  $upscope $end
 $upscope $end
$enddefinitions $end


#0
1#
0$
0%
0&
0'
b1101 (
b0000 )
1*
b0000 +
#1
0#
1$
b0011 (
0*
#2
1#
b0100 (
b0100 )
1*
b0100 +
#3
0#
b0011 (
0*
#4
1#
1&
b0111 (
b0111 )
1*
b0111 +
#5
0#
b1101 (
0*
#6
1#
b1111 (
#7
0#
b1110 (
1*
#8
1#
b1101 (
0*
#9
0#
b0000 (
1*
#10
1#
b1111 (
0*
#11
0#
b1110 (
#12
1#
b0111 (
1*
#13
0#
b1011 (
0*
#14
1#
b0001 (
#15
0#
1*
#16
1#
b0011 (
0*
#17
0#
b1111 (
1*
#18
1#
b1010 (
0*
#19
0#
b0101 (
#20
1#
b1011 (
b1011 )
1*
b1011 +
#21
0#
b0110 (
0*
#22
1#
b0111 (
b0111 )
1*
b0111 +
#23
0#
b1010 (
0*
#24
1#
b0101 (
b0101 )
1*
b0101 +
#25
0#
b0010 (
#26
1#
b1111 (
b1111 )
b1111 +
#27
0#
b0111 (
0*
#28
1#
b0001 (
#29
0#
b1001 (
#30
1#
b0011 (
#31
0#
1*
#32
1#
b1101 (
0*
#33
0#
b0010 (
1*
#34
1#
0&
b0100 (
b0100 )
b0100 +
#35
0#
b0011 (
0*
#36
1#
1&
b0001 (
b0001 )
1*
b0001 +
#37
0#
b1010 (
0*
#38
1#
b1101 (
b1101 )
1*
b1101 +
#39
0#
#40
1#
0&
b1010 (
b1010 )
b1010 +
#41
0#
b0010 (
0*
#42
1#
b1100 (
#43
0#
b0010 (
1*
#44
1#
1&
b1101 (
b1101 )
b1101 +
#45
0#
b0001 (
#46
1#
b1010 (
0*
#47
0#
b0010 (
1*
#48
1#
b1101 (
#49
0#
0*
#50
1#
1*
#51
0#
b0101 (
#52
1#
b0111 (
0*
#53
0#
b1111 (
#54
1#
b1011 (
#55
0#
b1001 (
#56
1#
0&
b1010 (
b1010 )
1*
b1010 +
#57
0#
b0001 (
0*
#58
1#
b0100 (
#59
0#
b1001 (
#60
1#
b1101 (
#61
0#
b1001 (
1*
#62
1#
b1011 (
0*
#63
0#
b0010 (
#64
1#
1&
b1101 (
b1101 )
1*
b1101 +
#65
0#
b1111 (
0*
#66
1#
b0001 (
#67
0#
1*
#68
1#
b1010 (
0*
#69
0#
#70
1#
b0011 (
b0011 )
1*
b0011 +
#71
0#
b0001 (
0*
#72
1#
b0111 (
b0111 )
1*
b0111 +
#73
0#
b1001 (
#74
1#
b0000 (
0*
#75
0#
b0011 (
1*
#76
1#
b1001 (
b1001 )
b1001 +
#77
0#
b1011 (
0*
#78
1#
b1101 (
#79
0#
b0100 (
1*
#80
1#
b1001 (
#81
0#
b0101 (
0*
#82
1#
b0110 (
#83
0#
b1110 (
#84
1#
0&
b1110 )
1*
b1110 +
#85
0#
b1011 (
0*
#86
1#
b0100 (
#87
0#
b1111 (
#88
1#
b0100 (
#89
0#
b1101 (
#90
1#
1&
b0001 (
b0001 )
1*
b0001 +
#91
0#
0*
#92
1#
0&
b1000 (
b1000 )
1*
b1000 +
#93
0#
b1001 (
#94
1#
b1011 (
0*
#95
0#
b1100 (
#96
1#
b1010 (
b1010 )
1*
b1010 +
#97
0#
b0001 (
#98
1#
b1111 (
0*
#99
0#
b1000 (
1*
#100
1#
0$
b0001 (
b0000 )
b0000 +
#101
0#
1$
b0101 (
#102
1#
1&
b0011 (
b0011 )
b0011 +
#103
0#
b0010 (
#104
1#
b0001 (
b0001 )
b0001 +
#105
0#
b1001 (
0*
#106
1#
b1011 (
#107
0#
b0101 (
#108
1#
b1111 (
b1111 )
1*
b1111 +
#109
0#
b0100 (
0*
#110
1#
b0101 (
#111
0#
b1010 (
#112
1#
b0011 (
#113
0#
b0101 (
#114
1#
b1011 (
b1011 )
1*
b1011 +
#115
0#
b0101 (
0*
#116
1#
b1100 (
#117
0#
b0110 (
1*
#118
1#
0&
b1000 (
b1000 )
b1000 +
#119
0#
b1011 (
0*
#120
1#
b0011 (
#121
0#
b1100 (
1*
#122
1#
0*
#123
0#
b0100 (
#124
1#
b1110 (
b1110 )
1*
b1110 +
#125
0#
b1010 (
#126
1#
b0000 (
b0000 )
b0000 +
#127
0#
b0111 (
#128
1#
b1011 (
0*
#129
0#
b1101 (
#130
1#
1&
b1011 (
b1011 )
1*
b1011 +
#131
0#
b0000 (
0*
#132
1#
b1100 (
#133
0#
b1101 (
#134
1#
b1011 (
1*
#135
0#
b0100 (
0*
#136
1#
b0111 (
#137
0#
b1101 (
1*
#138
1#
b1011 (
0*
#139
0#
b1110 (
1*
#140
1#
b0101 (
0*
#141
0#
b0111 (
1*
#142
1#
0&
b1000 (
b1000 )
b1000 +
#143
0#
b0100 (
#144
1#
1&
b1111 (
b1111 )
b1111 +
#145
0#
b0000 (
#146
1#
b1001 (
0*
#147
0#
b0100 (
#148
1#
b1001 (
b1001 )
1*
b1001 +
#149
0#
#150
1#
b0101 (
0*
#151
0#
b1100 (
#152
1#
b0110 (
#153
0#
b1011 (
1*
#154
1#
0&
b1000 (
b1000 )
b1000 +
#155
0#
b0010 (
#156
1#
b1100 (
b1100 )
b1100 +
#157
0#
b0000 (
#158
1#
b0010 (
b0010 )
b0010 +
#159
0#
b0100 (
#160
1#
b0101 (
0*
#161
0#
b1011 (
#162
1#
b0111 (
#163
0#
b0110 (
#164
1#
b0101 (
#165
0#
#166
1#
b1100 (
#167
0#
b1101 (
#168
1#
1&
b0111 (
b0111 )
1*
b0111 +
#169
0#
b1111 (
0*
#170
1#
b1001 (
b1001 )
1*
b1001 +
#171
0#
0*
#172
1#
b0101 (
b0101 )
1*
b0101 +
#173
0#
b0011 (
#174
1#
b1101 (
b1101 )
b1101 +
#175
0#
b0011 (
#176
1#
b1110 (
0*
#177
0#
#178
1#
b0110 (
#179
0#
b1001 (
#180
1#
b0111 (
#181
0#
b0001 (
1*
#182
1#
b0000 (
0*
#183
0#
b1100 (
1*
#184
1#
0&
b1110 (
b1110 )
b1110 +
#185
0#
#186
1#
b1111 (
0*
#187
0#
b1010 (
#188
1#
#189
0#
b0000 (
1*
#190
1#
b0011 (
0*
#191
0#
b0111 (
1*
#192
1#
b0000 (
b0000 )
b0000 +
#193
0#
b1110 (
0*
#194
1#
b0000 (
1*
#195
0#
b0100 (
#196
1#
b0000 (
#197
0#
b1101 (
0*
#198
1#
#199
0#
b1011 (
1*
#200
1#
0$
b1101 (
#201
0#
1$
b0111 (
#202
1#
b1000 (
0*
#203
0#
#204
1#
b0110 (
#205
0#
b1001 (
#206
1#
b0001 (
#207
0#
b0000 (
1*
#208
1#
b0111 (
0*
#209
0#
b1010 (
#210
1#
b1001 (
#211
0#
b0100 (
1*
#212
1#
1&
b1011 (
b1011 )
b1011 +
#213
0#
b0000 (
0*
#214
1#
0&
b0110 (
b0110 )
1*
b0110 +
#215
0#
b1011 (
#216
1#
1&
b0011 (
b0011 )
b0011 +
#217
0#
b0101 (
#218
1#
b0001 (
b0001 )
b0001 +
#219
0#
b1111 (
0*
#220
1#
b1010 (
#221
0#
b1101 (
#222
1#
b0001 (
1*
#223
0#
b1001 (
#224
1#
b0101 (
b0101 )
b0101 +
#225
0#
b0110 (
#226
1#
0&
b1000 (
b1000 )
b1000 +
#227
0#
b0011 (
#228
1#
b1100 (
b1100 )
b1100 +
#229
0#
b1001 (
#230
1#
1&
b0001 (
b0001 )
b0001 +
#231
0#
b0100 (
0*
#232
1#
b1111 (
#233
0#
b0010 (
1*
#234
1#
b0101 (
b0101 )
b0101 +
#235
0#
b1000 (
#236
1#
b0000 (
0*
#237
0#
b0110 (
#238
1#
b0010 (
#239
0#
b1011 (
1*
#240
1#
b1111 (
b1111 )
b1111 +
#241
0#
b0111 (
0*
#242
1#
b0001 (
b0001 )
1*
b0001 +
#243
0#
b1101 (
#244
1#
0&
b0110 (
b0110 )
b0110 +
#245
0#
0*
#246
1#
1&
b1101 (
b1101 )
1*
b1101 +
#247
0#
b1110 (
#248
1#
b0111 (
b0111 )
b0111 +
#249
0#
b1101 (
0*
#250
1#
b1110 (
#251
0#
b1111 (
#252
1#
b1011 (
#253
0#
b1000 (
#254
1#
0&
b0010 (
b0010 )
1*
b0010 +
#255
0#
b0111 (
#256
1#
b0010 (
0*
#257
0#
b0011 (
1*
#258
1#
b0000 (
0*
#259
0#
b1001 (
#260
1#
1&
b1011 (
b1011 )
1*
b1011 +
#261
0#
b1101 (
#262
1#
b0001 (
0*
#263
0#
#264
1#
b1101 (
b1101 )
1*
b1101 +
#265
0#
b0001 (
0*
#266
1#
b0011 (
#267
0#
b1010 (
1*
#268
1#
b0001 (
b0001 )
b0001 +
#269
0#
b0100 (
0*
#270
1#
0&
b1100 (
b1100 )
1*
b1100 +
#271
0#
#272
1#
b0100 (
b0100 )
b0100 +
#273
0#
b0010 (
#274
1#
1&
b0001 (
b0001 )
b0001 +
#275
0#
b1011 (
0*
#276
1#
b0110 (
#277
0#
b0001 (
#278
1#
0&
b1110 (
b1110 )
1*
b1110 +
#279
0#
b1111 (
#280
1#
b1000 (
0*
#281
0#
b0101 (
#282
1#
b1000 (
#283
0#
b1110 (
1*
#284
1#
b0010 (
0*
#285
0#
b1110 (
#286
1#
b1101 (
#287
0#
b0010 (
1*
#288
1#
b1110 (
#289
0#
b0011 (
#290
1#
b0001 (
0*
#291
0#
b1010 (
#292
1#
b1111 (
#293
0#
#294
1#
b1110 (
1*
#295
0#
b0100 (
#296
1#
b1110 (
0*
#297
0#
b1101 (
1*
#298
1#
b1011 (
0*
#299
0#
b0100 (
1*
