practice-circuits/tff.v
`default_nettype none

// DFF with async reset
module tff (
    clk,
    t_in,
    n_reset,
    data_out
);

    input wire clk;
    input wire t_in;
    input wire n_reset;
    output reg data_out;

    always @ (posedge clk or negedge n_reset) begin
        if (~n_reset) begin
            data_out <= 0;
        end else begin
            if (t_in) begin
                data_out <= ~data_out;
            end
        end
    end
endmodule

practice-circuits/tff-trace.vcd
$version Generated by VerilatedVcd $end
$timescale 1ps $end
 $scope module TOP $end
  $var wire 1 # clk $end
  $var wire 1 $ t_in $end
  $var wire 1 % n_reset $end
  $var wire 1 & data_out $end
  $scope module tff $end
   $var wire 1 # clk $end
   $var wire 1 $ t_in $end
   $var wire 1 % n_reset $end
   $var wire 1 & data_out $end
  $upscope $end
 $upscope $end
$enddefinitions $end


#0
1#
0$
0%
0&
#1
0#
1%
#2
1#
1$
1&
#3
0#
0$
#4
1#
#5
0#
1$
#6
1#
0&
#7
0#
#8
1#
0$
#9
0#
1$
#10
1#
0$
#11
0#
#12
1#
#13
0#
#14
1#
1$
1&
#15
0#
0$
#16
1#
#17
0#
1$
#18
1#
0$
#19
0#
#20
1#
1$
0&
#21
0#
#22
1#
1&
#23
0#
0$
#24
1#
#25
0#
1$
#26
1#
0&
#27
0#
0$
#28
1#
#29
0#
#30
1#
1$
1&
#31
0#
0$
#32
1#
#33
0#
1$
#34
1#
0&
#35
0#
#36
1#
1&
#37
0#
#38
1#
0$
#39
0#
1$
#40
1#
0$
#41
0#
#42
1#
#43
0#
1$
#44
1#
0&
#45
0#
0$
#46
1#
#47
0#
1$
#48
1#
1&
#49
0#
#50
1#
0$
#51
0#
#52
1#
1$
0&
#53
0#
0$
#54
1#
#55
0#
1$
#56
1#
1&
#57
0#
0$
#58
1#
1$
0&
#59
0#
0$
#60
1#
#61
0#
1$
#62
1#
1&
#63
0#
#64
1#
0$
#65
0#
1$
#66
1#
0&
#67
0#
#68
1#
1&
#69
0#
#70
1#
0$
#71
0#
1$
#72
1#
0$
#73
0#
1$
#74
1#
0&
#75
0#
0$
#76
1#
1$
1&
#77
0#
0$
#78
1#
1$
0&
#79
0#
#80
1#
1&
#81
0#
#82
1#
0&
#83
0#
0$
#84
1#
#85
0#
1$
#86
1#
0$
#87
0#
1$
#88
1#
0$
#89
0#
#90
1#
#91
0#
#92
1#
1$
1&
#93
0#
0$
#94
1#
1$
0&
#95
0#
#96
1#
1&
#97
0#
#98
1#
0$
#99
0#
1$
#100
1#
0$
0%
0&
#101
0#
1%
#102
1#
#103
0#
1$
#104
1#
0$
#105
0#
#106
1#
1$
1&
#107
0#
#108
1#
0$
#109
0#
#110
1#
#111
0#
1$
#112
1#
0$
#113
0#
1$
#114
1#
0&
#115
0#
#116
1#
1&
#117
0#
0$
#118
1#
#119
0#
1$
#120
1#
0$
#121
0#
1$
#122
1#
0$
#123
0#
#124
1#
#125
0#
1$
#126
1#
0&
#127
0#
0$
#128
1#
1$
1&
#129
0#
0$
#130
1#
1$
0&
#131
0#
0$
#132
1#
1$
1&
#133
0#
0$
#134
1#
1$
0&
#135
0#
#136
1#
0$
#137
0#
1$
#138
1#
1&
#139
0#
#140
1#
0$
#141
0#
1$
#142
1#
0&
#143
0#
0$
#144
1#
#145
0#
1$
#146
1#
1&
#147
0#
0$
#148
1#
1$
0&
#149
0#
0$
#150
1#
#151
0#
#152
1#
#153
0#
1$
#154
1#
1&
#155
0#
0$
#156
1#
1$
0&
#157
0#
#158
1#
1&
#159
0#
#160
1#
0&
#161
0#
#162
1#
0$
#163
0#
#164
1#
1$
1&
#165
0#
#166
1#
0$
#167
0#
1$
#168
1#
0&
#169
0#
#170
1#
0$
#171
0#
#172
1#
1$
1&
#173
0#
#174
1#
0&
#175
0#
0$
#176
1#
#177
0#
1$
#178
1#
1&
#179
0#
0$
#180
1#
#181
0#
1$
#182
1#
0&
#183
0#
0$
#184
1#
1$
1&
#185
0#
0$
#186
1#
1$
0&
#187
0#
#188
1#
0$
#189
0#
#190
1#
#191
0#
#192
1#
1$
1&
#193
0#
#194
1#
0&
#195
0#
0$
#196
1#
1$
1&
#197
0#
#198
1#
0&
#199
0#
#200
1#
0$
0%
#201
0#
1%
#202
1#
1$
1&
#203
0#
0$
#204
1#
1$
0&
#205
0#
#206
1#
1&
#207
0#
#208
1#
0&
#209
0#
0$
#210
1#
1$
1&
#211
0#
#212
1#
0$
#213
0#
1$
#214
1#
0&
#215
0#
0$
#216
1#
1$
1&
#217
0#
#218
1#
0$
#219
0#
1$
#220
1#
0&
#221
0#
0$
#222
1#
#223
0#
1$
#224
1#
0$
#225
0#
#226
1#
#227
0#
#228
1#
1$
1&
#229
0#
#230
1#
0$
#231
0#
1$
#232
1#
0$
#233
0#
1$
#234
1#
0&
#235
0#
#236
1#
0$
#237
0#
1$
#238
1#
0$
#239
0#
#240
1#
#241
0#
1$
#242
1#
0$
#243
0#
#244
1#
1$
1&
#245
0#
#246
1#
0&
#247
0#
0$
#248
1#
#249
0#
1$
#250
1#
0$
#251
0#
1$
#252
1#
0$
#253
0#
#254
1#
#255
0#
#256
1#
#257
0#
1$
#258
1#
0$
#259
0#
1$
#260
1#
1&
#261
0#
#262
1#
0&
#263
0#
#264
1#
1&
#265
0#
#266
1#
0$
#267
0#
#268
1#
#269
0#
1$
#270
1#
0$
#271
0#
1$
#272
1#
0&
#273
0#
#274
1#
0$
#275
0#
1$
#276
1#
1&
#277
0#
0$
#278
1#
1$
0&
#279
0#
#280
1#
1&
#281
0#
0$
#282
1#
#283
0#
1$
#284
1#
0$
#285
0#
#286
1#
#287
0#
1$
#288
1#
0&
#289
0#
0$
#290
1#
#291
0#
#292
1#
#293
0#
#294
1#
1$
1&
#295
0#
#296
1#
0&
#297
0#
#298
1#
1&
#299
0#
0$
